iotile/__init__.py
iotile/fixture/__init__.py
iotile/fixture/device_fixture.py
iotile/fixture/filesystem_fixture.py
iotile/fixture/subprocess_fixture.py
iotile/mock/__init__.py
iotile/mock/mock_ble.py
iotile/mock/mock_resolver.py
iotile/mock/devices/__init__.py
iotile/mock/devices/noapp.py
iotile/mock/devices/realtime_test_device.py
iotile/mock/devices/report_test_device.py
iotile/mock/devices/report_test_device_proxy.py
iotile/mock/devices/sg_test_device.py
iotile/mock/devices/simple_virtual_device.py
iotile/mock/devices/simple_virtual_proxy.py
iotile/mock/devices/tracing_test_device.py
iotile/test_scripts/__init__.py
iotile/test_scripts/prepare_device.py
iotile_test-2.1.0.dist-info/LICENSE.md
iotile_test-2.1.0.dist-info/METADATA
iotile_test-2.1.0.dist-info/WHEEL
iotile_test-2.1.0.dist-info/entry_points.txt
iotile_test-2.1.0.dist-info/top_level.txt
iotile_test-2.1.0.dist-info/RECORD
